[{"avKeys":["BAYERN MUNICH"],"key":"bayern","name":"Bayern Munich","country":"de"},{"avKeys":["WERDER BREMEN"],"key":"werder_bremen","name":"Werder Bremen","country":"de"},{"avKeys":["MONCHENGLADBACH"],"key":"monchengladbach","name":"Monchengladbach","country":"de"},{"avKeys":["BAYER LEVERKUSEN"],"key":"bayer_leverkusen","name":"Bayer Leverkusen","country":"de"},{"avKeys":["MAINZ 05"],"key":"mainz","name":"Mainz 05","country":"de"},{"avKeys":["BORUSSIA DORTMUND"],"key":"dortmund","name":"Borussia Dortmund","country":"de"},{"avKeys":["SCHALKE 04"],"key":"schalke","name":"Schalke 04","country":"de"},{"avKeys":["EINTRACHT FRANKFURT"],"key":"frankfurt","name":"Eintracht Frankfurt","country":"de"},{"avKeys":["FREIBURG"],"key":"freiburg","name":"Freiburg","country":"de"},{"avKeys":["HERTHA BERLIN"],"key":"hertha_berlin","name":"Hertha Berlin","country":"de"},{"avKeys":["HAMBURG","HAMBURGER"],"key":"hamburg","name":"Hamburg","country":"de"},{"avKeys":["LEIPZIG","RB LEIPZIG"],"key":"leipzig","name":"RB Leipzig","country":"de"},{"avKeys":["ARSENAL"],"key":"arsenal","name":"Arsenal","country":"en"},{"avKeys":["CHELSEA"],"key":"chelsea","name":"Chelsea","country":"en"},{"avKeys":["LEICESTER","LEICESTER CITY"],"key":"leicester","name":"Leicester","country":"en"},{"avKeys":["LIVERPOOL"],"key":"liverpool","name":"Liverpool","country":"en"},{"avKeys":["SOUTHAMPTON"],"key":"southampton","name":"Southampton","country":"en"},{"avKeys":["WATFORD"],"key":"watford","name":"Watford","country":"en"},{"avKeys":["MANCHESTER UNITED","MANCHESTER UTD"],"key":"manchester_utd","name":"Manchester United","country":"en"},{"avKeys":["MANCHESTER CITY"],"key":"manchester_city","name":"Manchester City","country":"en"},{"avKeys":["TOTTENHAM","TOTTENHAM HOTSPUR"],"key":"tottenham","name":"Tottenham","country":"en"},{"avKeys":["WEST HAM","WEST HAM UNITED","WEST HAM UTD"],"key":"west_ham","name":"West Ham","country":"en"},{"avKeys":["EVERTON"],"key":"everton","name":"Everton","country":"en"},{"avKeys":["BURNLEY"],"key":"burnley","name":"Burnley","country":"en"},{"avKeys":["HULL","HULL CITY"],"key":"hull","name":"Hull City","country":"en"},{"avKeys":["CRYSTAL PALACE"],"key":"crystal_palace","name":"Crystal Palace","country":"en"},{"avKeys":["STOKE","STOKE CITY"],"key":"stoke","name":"Stoke City","country":"en"},{"avKeys":["SWANSEA","SWANSEA CITY"],"key":"swansea","name":"Swansea","country":"en"},{"avKeys":["SUNDERLAND"],"key":"sunderland","name":"Sunderland","country":"en"},{"avKeys":["SOUTHAMPTON"],"key":"southampton","name":"southampton","country":"en"},{"avKeys":["MIDDLESBROUGH"],"key":"middlesbrough","name":"middlesbrough","country":"en"},{"avKeys":["BOURNEMOUTH","AFC BOURNEMOUTH"],"key":"bournemouth","name":"Bournemouth","country":"en"},{"avKeys":["REAL MADRID"],"key":"real_madrid","name":"Real Madrid","country":"es"},{"avKeys":["OSASUNA"],"key":"osasuna","name":"Osasuna","country":"es"},{"avKeys":["MALAGA"],"key":"malaga","name":"Malaga","country":"es"},{"avKeys":["VILLARREAL"],"key":"villareal","name":"Villareal","country":"es"},{"avKeys":["GRANADA"],"key":"granada","name":"Granada","country":"es"},{"avKeys":["ALAVES","DEPORTIVO ALAVES"],"key":"alaves","name":"Alaves","country":"es"},{"avKeys":["ATLETICO DE MADRID","ATLETICO MADRID"],"key":"atletico_madrid","name":"Atletico de Madrid","country":"es"},{"avKeys":["EIBAR"],"key":"eibar","name":"Eibar","country":"es"},{"avKeys":["DEPORTIVO","DEPORTIVO LA CORUNA"],"key":"deportivo","name":"Deportivo de la Coruña","country":"es"},{"avKeys":["LEGANES"],"key":"leganes","name":"Leganes","country":"es"},{"avKeys":["CELTA","CELTA DE VIGO","CELTA VIGO"],"key":"celta","name":"Celta","country":"es"},{"avKeys":["BETIS","REAL BETIS"],"key":"betis","name":"Real Betis","country":"es"},{"avKeys":["BARCELONA","FC BARCELONA"],"key":"barcelona","name":"FC Barcelona","country":"es"},{"avKeys":["ESPANYOL"],"key":"espanyol","name":"Espanyol","country":"es"},{"avKeys":["SEVILLA","SEVILLA FC"],"key":"sevilla","name":"Sevilla FC","country":"es"},{"avKeys":["ATHLETIC CLUB","ATHLETIC BILBAO","ATHLETIC DE BILBAO"],"key":"athletic","name":"Athletic de Bilbao","country":"es"},{"avKeys":["SPORTING GIJON","SPORTING DE GIJON"],"key":"sporting","name":"Sporting Gijon","country":"es"},{"avKeys":["REAL SOCIEDAD"],"key":"real_sociedad","name":"Real Sociedad","country":"es"},{"avKeys":["LAS PALMAS"],"key":"las_palmas","name":"Las Palmas","country":"es"},{"avKeys":["VALENCIA"],"key":"valencia","name":"Valencia","country":"es"},{"avKeys":["ZARAGOZA","REAL ZARAGOZA"],"key":"zaragoza","name":"Real Zaragoza","country":"es"},{"avKeys":["ELCHE"],"key":"elche","name":"Elche","country":"es"},{"avKeys":["GIRONA"],"key":"girona","name":"Girona","country":"es"},{"avKeys":["LUGO"],"key":"lugo","name":"Lugo","country":"es"},{"avKeys":["SEVILLA ATLETICO"],"key":"sevilla_atletico","name":"Sevilla Atletico","country":"es"},{"avKeys":["TENERIFE"],"key":"tenerife","name":"Tenerife","country":"es"},{"avKeys":["ALCORCON"],"key":"alcorcon","name":"Alcorcon","country":"es"},{"avKeys":["LEVANTE"],"key":"levante","name":"Levante","country":"es"},{"avKeys":["VALLADOLID"],"key":"valladolid","name":"Valladolid","country":"es"},{"avKeys":["RAYO VALLECANO"],"key":"rayo_vallecano","name":"Rayo Vallecano","country":"es"},{"avKeys":["NUMANCIA"],"key":"numancia","name":"Numancia","country":"es"},{"avKeys":["GETAFE"],"key":"getafe","name":"Getafe","country":"es"},{"avKeys":["CORDOBA"],"key":"cordoba","name":"Cordoba","country":"es"},{"avKeys":["UCAM MURCIA"],"key":"ucam_murcia","name":"UCAM Murcia","country":"es"},{"avKeys":["MALLORCA","REAL MALLORCA"],"key":"mallorca","name":"Mallorca","country":"es"},{"avKeys":["CADIZ"],"key":"cadiz","name":"Cadiz","country":"es"},{"avKeys":["HUESCA","SD HUESCA"],"key":"huesca","name":"Huesca","country":"es"},{"avKeys":["OVIEDO","REAL OVIEDO"],"key":"oviedo","name":"Real Oviedo","country":"es"},{"avKeys":["ALMERIA"],"key":"almeria","name":"Almeria","country":"es"},{"avKeys":["REUS"],"key":"reus","name":"Reus","country":"es"},{"avKeys":["LAZIO"],"key":"lazio","name":"Lazio","country":"it"},{"avKeys":["CHIEVO VERONA"],"key":"chievo","name":"Chievo Verona","country":"it"},{"avKeys":["TORINO"],"key":"torino","name":"Torino","country":"it"},{"avKeys":["ATALANTA"],"key":"atalanta","name":"Atalanta","country":"it"},{"avKeys":["UDINESE"],"key":"udinese","name":"Udinese","country":"it"},{"avKeys":["AC MILAN"],"key":"milan","name":"AC Milan","country":"it"},{"avKeys":["SASSUOLO"],"key":"sassuolo","name":"Sassuolo","country":"it"},{"avKeys":["JUVENTUS"],"key":"juventus","name":"Juventus","country":"it"},{"avKeys":["NAPOLI"],"key":"napoli","name":"Napoli","country":"it"},{"avKeys":["PALERMO"],"key":"palermo","name":"Palermo","country":"it"},{"avKeys":["INTER MILAN"],"key":"inter","name":"Inter Milan","country":"it"},{"avKeys":["PESCARA"],"key":"pescara","name":"Pescara","country":"it"},{"avKeys":["BOLONIA","BOLOGNA"],"key":"bologna","name":"Bolonia","country":"it"},{"avKeys":["CAGLIARI"],"key":"cagliari","name":"Cagliari","country":"it"},{"avKeys":["CROTONE"],"key":"crotone","name":"Crotone","country":"it"},{"avKeys":["EMPOLI"],"key":"empoli","name":"Empoli","country":"it"},{"avKeys":["FIORENTINA"],"key":"fiorentina","name":"Fiorentina","country":"it"},{"avKeys":["GENOA"],"key":"genoa","name":"Genoa","country":"it"},{"avKeys":["ROMA"],"key":"genoa","name":"Roma","country":"it"},{"avKeys":["SAMPDORIA"],"key":"sampdoria","name":"Sampdoria","country":"it"},{"avKeys":["UDINESE"],"key":"udinese","name":"Udinese","country":"it"},{"avKeys":["NEW YORK KNICKS"],"key":"knicks","name":"New York Knicks","country":"us"},{"avKeys":["ATLANTA HAWKS"],"key":"hawks","name":"Atlanta Hawks","country":"us"},{"avKeys":["OKLAHOMA CITY THUNDER"],"key":"thunder","name":"Oklahoma City Thunder","country":"us"},{"avKeys":["CLEVELAND CAVALIERS"],"key":"cavaliers","name":"Cleveland Cavaliers","country":"us"},{"avKeys":["GOLDEN STATE WARRIORS"],"key":"warriors","name":"Golden State Warriors","country":"us"},{"avKeys":["HOUSTON ROCKETS"],"key":"rockets","name":"Houston Rockets","country":"us"}]